email_generator_pkg/__init__.py
email_generator_pkg/cli.py
email_generator_pkg/generator.py
email_generator_pkg/data/email_service.json
email_list_generator-1.0.0.dist-info/licenses/LICENSE
email_list_generator-1.0.0.dist-info/METADATA
email_list_generator-1.0.0.dist-info/WHEEL
email_list_generator-1.0.0.dist-info/entry_points.txt
email_list_generator-1.0.0.dist-info/top_level.txt
email_list_generator-1.0.0.dist-info/RECORD
