Metadata-Version: 2.4
Name: email-list-generator
Version: 1.0.0
Summary: Generates potential email addresses based on target info for ethical testing.
Author-email: HackingRepo <cs7778503@gmail.com>
License: 
Keywords: email,generator,osint,pentesting,security,email-list,email_list
Classifier: Programming Language :: Python :: 3
Classifier: License :: OSI Approved :: MIT License
Classifier: Operating System :: OS Independent
Classifier: Intended Audience :: Developers
Classifier: Topic :: Security
Classifier: Topic :: Utilities
Requires-Python: >=3.9
License-File: LICENSE
Requires-Dist: termcolor
Dynamic: license-file
